easyecs/__init__.py
easyecs/cli.py
easyecs/cloudformation/__init__.py
easyecs/cloudformation/auto_destruction/harakiri.py
easyecs/cloudformation/client.py
easyecs/cloudformation/fetch.py
easyecs/cloudformation/stack/__init__.py
easyecs/cloudformation/stack/create.py
easyecs/cloudformation/stack/delete.py
easyecs/cloudformation/stack/update.py
easyecs/cloudformation/stack/waiter.py
easyecs/cloudformation/template/__init__.py
easyecs/cloudformation/template/task_definition.py
easyecs/command/__init__.py
easyecs/command/event/synchronize_event_handler.py
easyecs/docker/__init__.py
easyecs/helpers/__init__.py
easyecs/helpers/color.py
easyecs/helpers/common.py
easyecs/helpers/exceptions.py
easyecs/helpers/loader.py
easyecs/helpers/selector.py
easyecs/helpers/settings.py
easyecs/helpers/signal.py
easyecs/model/ecs.py
easyecs-0.25.0.dist-info/METADATA
easyecs-0.25.0.dist-info/WHEEL
easyecs-0.25.0.dist-info/entry_points.txt
easyecs-0.25.0.dist-info/RECORD
