Metadata-Version: 2.4
Name: easyecs
Version: 0.25.0
Summary: 
Author: BONVARLET Benjamin
Author-email: benjaminbonvarlet96@gmail.com
Requires-Python: >=3.11,<4.0
Classifier: Programming Language :: Python :: 3
Classifier: Programming Language :: Python :: 3.11
Classifier: Programming Language :: Python :: 3.12
Classifier: Programming Language :: Python :: 3.13
Classifier: Programming Language :: Python :: 3.14
Requires-Dist: aws-cdk-lib (>=2.89.0,<3.0.0)
Requires-Dist: boto3 (>=1.28.14,<2.0.0)
Requires-Dist: click (>=8.1.6,<9.0.0)
Requires-Dist: jinja2 (>=3.1.6,<4.0.0)
Requires-Dist: paramiko (>=4.0.0,<5.0.0)
Requires-Dist: pydantic (>=2.1.1,<3.0.0)
Requires-Dist: pyfzf (>=0.3.1,<0.4.0)
Requires-Dist: pyyaml (>=6.0.1,<7.0.0)
Requires-Dist: scp (>=0.15.0,<0.16.0)
Requires-Dist: watchdog (>=3.0.0,<4.0.0)
